.svnignore
README.txt
setup.py
TGOpenIDLogin.egg-info/PKG-INFO
TGOpenIDLogin.egg-info/SOURCES.txt
TGOpenIDLogin.egg-info/dependency_links.txt
TGOpenIDLogin.egg-info/entry_points.txt
TGOpenIDLogin.egg-info/not-zip-safe
TGOpenIDLogin.egg-info/paster_plugins.txt
TGOpenIDLogin.egg-info/requires.txt
TGOpenIDLogin.egg-info/sqlobject.txt
TGOpenIDLogin.egg-info/top_level.txt
tgopenidlogin/__init__.py
tgopenidlogin/controllers.py
tgopenidlogin/release.py
tgopenidlogin/widgets.py
tgopenidlogin/static/css/openid.css
tgopenidlogin/static/images/empty
tgopenidlogin/static/javascript/empty
tgopenidlogin/templates/__init__.py
tgopenidlogin/templates/login.kid
