Metadata-Version: 1.0
Name: TGOpenIDLogin
Version: 0.1
Summary: OpenID login controller for TurboGears
Home-page: http://nxsy.org/code/tgopenidlogin/
Author: Neil Blakey-Milner
Author-email: nbm@nxsy.org
License: MIT
Keywords: turbogears.widgets
Platform: UNKNOWN
Classifier: Development Status :: 3 - Alpha
Classifier: Operating System :: OS Independent
Classifier: Programming Language :: Python
Classifier: Topic :: Software Development :: Libraries :: Python Modules
Classifier: Framework :: TurboGears
Classifier: Framework :: TurboGears :: Widgets
